collective.tileindex-1.0.0a4-py3.11-nspkg.pth
collective/tileindex/__init__.py
collective/tileindex/configure.zcml
collective/tileindex/interfaces.py
collective/tileindex/permissions.zcml
collective/tileindex/profiles.zcml
collective/tileindex/setuphandlers.py
collective/tileindex/testing.py
collective/tileindex/upgrades.py
collective/tileindex/utils.py
collective/tileindex/browser/__init__.py
collective/tileindex/browser/configure.zcml
collective/tileindex/browser/static/.gitkeep
collective/tileindex/indexers/__init__.py
collective/tileindex/indexers/configure.zcml
collective/tileindex/indexers/tile_types.py
collective/tileindex/locales/README.rst
collective/tileindex/locales/__init__.py
collective/tileindex/locales/collective.tileindex.pot
collective/tileindex/locales/update.sh
collective/tileindex/locales/en/LC_MESSAGES/collective.tileindex.mo
collective/tileindex/locales/en/LC_MESSAGES/collective.tileindex.po
collective/tileindex/locales/nl/LC_MESSAGES/collective.tileindex.mo
collective/tileindex/locales/nl/LC_MESSAGES/collective.tileindex.po
collective/tileindex/profiles/default/browserlayer.xml
collective/tileindex/profiles/default/catalog.xml
collective/tileindex/profiles/default/controlpanel.xml
collective/tileindex/profiles/default/metadata.xml
collective/tileindex/profiles/default/rolemap.xml
collective/tileindex/profiles/default/registry/main.xml
collective/tileindex/profiles/uninstall/browserlayer.xml
collective/tileindex/profiles/uninstall/controlpanel.xml
collective/tileindex/tests/__init__.py
collective/tileindex/tests/test_indexer_tile_types.py
collective/tileindex/tests/test_setup.py
collective/tileindex/tests/test_tile_types_view.py
collective/tileindex/tests/test_utils.py
collective/tileindex/views/__init__.py
collective/tileindex/views/configure.zcml
collective/tileindex/views/tile_types_overview.pt
collective/tileindex/views/tile_types_overview.py
collective/tileindex/views/tile_types_view.pt
collective/tileindex/views/tile_types_view.py
collective.tileindex-1.0.0a4.dist-info/LICENSE.GPL
collective.tileindex-1.0.0a4.dist-info/LICENSE.rst
collective.tileindex-1.0.0a4.dist-info/METADATA
collective.tileindex-1.0.0a4.dist-info/WHEEL
collective.tileindex-1.0.0a4.dist-info/entry_points.txt
collective.tileindex-1.0.0a4.dist-info/namespace_packages.txt
collective.tileindex-1.0.0a4.dist-info/top_level.txt
collective.tileindex-1.0.0a4.dist-info/RECORD
