Metadata-Version: 2.1
Name: collective.tileindex
Version: 1.0.0a4
Summary: An add-on for Plone
Home-page: https://github.com/collective/collective.tileindex
Author: Zest Software
Author-email: info@zestsoftware.nl
License: GPL version 2
Project-URL: PyPI, https://pypi.org/project/collective.tileindex/
Project-URL: Source, https://github.com/collective/collective.tileindex
Project-URL: Tracker, https://github.com/collective/collective.tileindex/issues
Keywords: Python Plone CMS
Classifier: Development Status :: 3 - Alpha
Classifier: Environment :: Web Environment
Classifier: Framework :: Plone
Classifier: Framework :: Plone :: Addon
Classifier: Framework :: Plone :: 5.2
Classifier: Framework :: Plone :: 6.0
Classifier: Programming Language :: Python
Classifier: Programming Language :: Python :: 3.8
Classifier: Programming Language :: Python :: 3.9
Classifier: Programming Language :: Python :: 3.10
Classifier: Programming Language :: Python :: 3.11
Classifier: Operating System :: OS Independent
Classifier: License :: OSI Approved :: GNU General Public License v2 (GPLv2)
Requires-Python: >=3.7
License-File: LICENSE.GPL
License-File: LICENSE.rst
Requires-Dist: setuptools
Requires-Dist: plone.api >=1.8.4
Provides-Extra: test
Requires-Dist: plone.app.testing ; extra == 'test'
Requires-Dist: plone.testing >=5.0.0 ; extra == 'test'
Requires-Dist: plone.app.blocks ; extra == 'test'
